fitter_python/__init__.py
fitter_python/console.py
fitter_python/wikipedia.py
fitter_python-0.1.0.dist-info/entry_points.txt
fitter_python-0.1.0.dist-info/LICENSE
fitter_python-0.1.0.dist-info/WHEEL
fitter_python-0.1.0.dist-info/METADATA
fitter_python-0.1.0.dist-info/RECORD
